setup.py
pulley/__init__.py
pulley/trading.py
pulley.egg-info/PKG-INFO
pulley.egg-info/SOURCES.txt
pulley.egg-info/dependency_links.txt
pulley.egg-info/requires.txt
pulley.egg-info/top_level.txt
pulley/algos/__init__.py
pulley/algos/olmar.py
pulley/brokers/__init__.py
pulley/brokers/broker.py
pulley/brokers/ib/__init__.py
pulley/brokers/ib/broker.py
pulley/brokers/ib/tws.py
pulley/reporting/__init__.py
pulley/reporting/pbo.py
pulley/reporting/report.py
pulley/reporting/yoy_metrics.py
pulley/zp/__init__.py
pulley/zp/finance/__init__.py
pulley/zp/finance/commission.py
pulley/zp/sources/__init__.py
pulley/zp/sources/query_source.py
pulley/zp/sources/redshift.py
pulley/zp/sources/splits_and_divs.py
pulley/zp/sources/yahoo.py