Metadata-Version: 1.0
Name: pulley
Version: 0.0.1
Summary: Live trading with zipline and swigibpy via Interactive Brokers.
Home-page: https://github.com/quantcluster/pulley.git
Author: Jimmie Goode
Author-email: jimmie@quantcluster.com
License: UNKNOWN
Platform: UNKNOWN
